README.md
setup.py
scitools/StringFunction.py
scitools/__init__.py
scitools/aplotter.py
scitools/avplotter.py
scitools/materials.py
scitools/pprint2.py
scitools/sound.py
scitools3.egg-info/PKG-INFO
scitools3.egg-info/SOURCES.txt
scitools3.egg-info/dependency_links.txt
scitools3.egg-info/top_level.txt