Metadata-Version: 1.0
Name: scitools3
Version: 1.0
Summary: 
